CHANGES.txt
LICENSE.txt
MANIFEST.in
requirements.txt
setup.py
bin/convert_congress
docs/README.txt
govtrack2csv/__init__.py
govtrack2csv/model.py
govtrack2csv/util.py
govtrack2csv.egg-info/PKG-INFO
govtrack2csv.egg-info/SOURCES.txt
govtrack2csv.egg-info/dependency_links.txt
govtrack2csv.egg-info/not-zip-safe
govtrack2csv.egg-info/pbr.json
govtrack2csv.egg-info/requires.txt
govtrack2csv.egg-info/top_level.txt