Metadata-Version: 1.0
Name: govtrack2csv
Version: 1.0.1
Summary: Toolset for converting govtrack data to csv.
Home-page: http://github.com/hackthefed/govtrack2csv
Author: Hack The Fed
Author-email: vance@hackthefed.com
License: GPL
Platform: UNKNOWN
